CHANGES.txt
LICENSE.txt
MANIFEST.in
README.txt
TODO.txt
setup.py
src/p01/__init__.py
src/p01.editor.egg-info/PKG-INFO
src/p01.editor.egg-info/SOURCES.txt
src/p01.editor.egg-info/dependency_links.txt
src/p01.editor.egg-info/namespace_packages.txt
src/p01.editor.egg-info/not-zip-safe
src/p01.editor.egg-info/requires.txt
src/p01.editor.egg-info/top_level.txt
src/p01/editor/README.txt
src/p01/editor/README_PY2.txt
src/p01/editor/__init__.py
src/p01/editor/configure.zcml
src/p01/editor/interfaces.py
src/p01/editor/jsonrpc.py
src/p01/editor/jsonrpc.zcml
src/p01/editor/tests.py
src/p01/editor/util.py
src/p01/editor/util.txt
src/p01/editor/widget.py
src/p01/editor/css/xEditorDialog.css
src/p01/editor/css/xEditorStyles.css
src/p01/editor/css/xeditor.css
src/p01/editor/demo/README.txt
src/p01/editor/demo/jquery-1.7.1.min.js
src/p01/editor/demo/qunit.css
src/p01/editor/demo/qunit.js
src/p01/editor/demo/test.html
src/p01/editor/img/blank.gif
src/p01/editor/img/blockStyle.png
src/p01/editor/img/block_address.png
src/p01/editor/img/block_blockquote.png
src/p01/editor/img/block_div.png
src/p01/editor/img/block_h1.png
src/p01/editor/img/block_h2.png
src/p01/editor/img/block_h3.png
src/p01/editor/img/block_h4.png
src/p01/editor/img/block_h5.png
src/p01/editor/img/block_h6.png
src/p01/editor/img/block_p.png
src/p01/editor/img/block_pre.png
src/p01/editor/img/btnBG.png
src/p01/editor/img/btnBlocks.gif
src/p01/editor/img/btnBold.gif
src/p01/editor/img/btnClose.gif
src/p01/editor/img/btnCustomObject.gif
src/p01/editor/img/btnDelete.gif
src/p01/editor/img/btnFlash.gif
src/p01/editor/img/btnHyperlink.gif
src/p01/editor/img/btnItalic.gif
src/p01/editor/img/btnJustifyCenter.gif
src/p01/editor/img/btnJustifyFull.gif
src/p01/editor/img/btnJustifyLeft.gif
src/p01/editor/img/btnJustifyRight.gif
src/p01/editor/img/btnMedia.gif
src/p01/editor/img/btnOrderedList.gif
src/p01/editor/img/btnPaste.gif
src/p01/editor/img/btnRedo.gif
src/p01/editor/img/btnRemoveFormat.gif
src/p01/editor/img/btnResize.gif
src/p01/editor/img/btnSource.gif
src/p01/editor/img/btnStyles.gif
src/p01/editor/img/btnUndo.gif
src/p01/editor/img/btnUnorderedList.gif
src/p01/editor/img/btns.png
src/p01/editor/img/close.gif
src/p01/editor/img/dialogBG.gif
src/p01/editor/img/spacer.gif
